FastML_With_EDA/AutoML.py
FastML_With_EDA/EDA_and_preprocessing.py
FastML_With_EDA/__init__.py
FastML_With_EDA-0.1.0.dist-info/LICENSE
FastML_With_EDA-0.1.0.dist-info/METADATA
FastML_With_EDA-0.1.0.dist-info/WHEEL
FastML_With_EDA-0.1.0.dist-info/top_level.txt
FastML_With_EDA-0.1.0.dist-info/RECORD
